deus_reader/__init__.py
deus_reader/deus_reader_classes.py
deus_reader-0.1.dist-info/DESCRIPTION.rst
deus_reader-0.1.dist-info/METADATA
deus_reader-0.1.dist-info/RECORD
deus_reader-0.1.dist-info/WHEEL
deus_reader-0.1.dist-info/metadata.json
deus_reader-0.1.dist-info/top_level.txt
