Metadata-Version: 2.0
Name: deus-reader
Version: 0.1
Summary: Tools for reading spherical profiles computed from the DEUS simulations.
Home-page: UNKNOWN
Author: Paul de Fromont
Author-email: paul.de-fromont@obspm.fr
License: MIT
Platform: UNKNOWN
Requires-Python: >=3
Requires-Dist: numpy
